polyanalyst6api/__init__.py
polyanalyst6api/api.py
polyanalyst6api/drive.py
polyanalyst6api/exceptions.py
polyanalyst6api/project.py
polyanalyst6api/report.py
polyanalyst6api-0.35.3.dist-info/LICENSE
polyanalyst6api-0.35.3.dist-info/METADATA
polyanalyst6api-0.35.3.dist-info/WHEEL
polyanalyst6api-0.35.3.dist-info/RECORD
