Metadata-Version: 2.1
Name: polyanalyst6api
Version: 0.35.3
Summary: polyanalyst6api is a PolyAnalyst API client for Python.
Home-page: https://github.com/Megaputer/polyanalyst6api-py
License: MIT
Keywords: megaputer,polyanalyst,polyanalyst6api,api
Author: yatmanov
Author-email: yatmanov@megaputer.ru
Requires-Python: >=3.7,<4.0
Classifier: License :: OSI Approved :: MIT License
Classifier: Programming Language :: Python :: 3
Classifier: Programming Language :: Python :: 3.7
Classifier: Programming Language :: Python :: 3.8
Classifier: Programming Language :: Python :: 3.9
Classifier: Programming Language :: Python :: 3.10
Classifier: Programming Language :: Python :: 3.11
Classifier: Programming Language :: Python :: 3.12
Classifier: Programming Language :: Python :: 3.13
Classifier: Topic :: Internet
Classifier: Topic :: Software Development :: Libraries :: Python Modules
Requires-Dist: pytus (>=0.2.1,<0.3.0)
Requires-Dist: requests (>=2.31,<3.0)
Requires-Dist: urllib3 (==1.26.18) ; python_version == "3.7"
Requires-Dist: urllib3 ; python_version >= "3.8"
Project-URL: Changelog, https://github.com/Megaputer/polyanalyst6api-py/blob/master/CHANGELOG.md
Project-URL: Documentation, https://polyanalyst6api-py.rtfd.io/
Project-URL: Repository, https://github.com/Megaputer/polyanalyst6api-py
